Workbook

Sheet Inputs
A1: COST MODEL - Day 1 S4. Yellow cells are inputs; everything else is a formula.
A2: Scenario: A - service desk ticket to structured record (the Day 2 task)
A3: Prices and their sources: sheet 'Sources'. Formulas explained: facilitator/cost_model.md
A5: Requests per working day | B5: 300 | C5: One request = one model call. A chat turn or an agent step is a request each.
A6: Working days per month | B6: 22
A7: Working hours per day | B7: 8 | C7: Hours the requests are spread over.
A8: Peak factor (busiest hour / average hour) | B8: 3 | C8: 3 is normal for a service desk: Sunday 08:00 after a long weekend.
A9: Input tokens per request | B9: 330 | C9: Prompt + context + the user's text. Scenario A: MEASURED, 250 system + ~80 ticket (Sources S10).
A10: Output tokens per request | B10: 60 | C10: Scenario A: one JSON record, measured mean 57.
A11: Share of input tokens served from cache | B11: 0.75 | C11: The part of the prompt that is identical every call (system prompt, tool list). 0 if unsure.
A12: Months to total over | B12: 12
A14: Derived
A15: Requests per month | B15: =B5*B6 | C15: Formula: requests/day x working days
A16: Input tokens per month | B16: =B15*B9
A17: Output tokens per month | B17: =B15*B10
A18: Peak requests per hour | B18: =B5/B7*B8 | C18: Formula: requests/day / working hours x peak factor. This sizes the VM, the monthly total sizes the bill.

Sheet API options
A1: VENDOR API COST. Prices are per 1M tokens (yellow = editable, see Sources). Costs are formulas.
H2: Formula: (uncached in x price + cached in x cached price + out x price) / 1e6
A3: Provider | B3: Model | C3: Input $/MTok | D3: Cached input $/MTok | E3: Output $/MTok | F3: Batch discount | G3: Source | H3: $ / month | I3: $ / month, batch | J3: $ / 1000 requests | K3: $ total (months)
A4: OpenAI | B4: gpt-5.4-mini | C4: 0.75 | D4: 0.075 | E4: 4.5 | F4: 0.5 | G4: S1 | H4: =(Inputs!$B$16*(1-Inputs!$B$11)*C4+Inputs!$B$16*Inputs!$B$11*D4+Inputs!$B$17*E4)/1000000 | I4: =IF(F4>0,H4*(1-F4),"-") | J4: =H4/Inputs!$B$15*1000 | K4: =H4*Inputs!$B$12
A5: OpenAI | B5: gpt-5.4 | C5: 2.5 | D5: 0.25 | E5: 15 | F5: 0.5 | G5: S1 | H5: =(Inputs!$B$16*(1-Inputs!$B$11)*C5+Inputs!$B$16*Inputs!$B$11*D5+Inputs!$B$17*E5)/1000000 | I5: =IF(F5>0,H5*(1-F5),"-") | J5: =H5/Inputs!$B$15*1000 | K5: =H5*Inputs!$B$12
A6: OpenAI | B6: gpt-5.6-luna | C6: 0.2 | D6: 0.02 | E6: 1.2 | F6: 0.5 | G6: S1 | H6: =(Inputs!$B$16*(1-Inputs!$B$11)*C6+Inputs!$B$16*Inputs!$B$11*D6+Inputs!$B$17*E6)/1000000 | I6: =IF(F6>0,H6*(1-F6),"-") | J6: =H6/Inputs!$B$15*1000 | K6: =H6*Inputs!$B$12
A7: OpenAI | B7: gpt-5.6-terra | C7: 2 | D7: 0.2 | E7: 12 | F7: 0.5 | G7: S1 | H7: =(Inputs!$B$16*(1-Inputs!$B$11)*C7+Inputs!$B$16*Inputs!$B$11*D7+Inputs!$B$17*E7)/1000000 | I7: =IF(F7>0,H7*(1-F7),"-") | J7: =H7/Inputs!$B$15*1000 | K7: =H7*Inputs!$B$12
A8: Anthropic | B8: Claude Haiku 4.5 | C8: 1 | D8: 0.1 | E8: 5 | F8: 0.5 | G8: S2 | H8: =(Inputs!$B$16*(1-Inputs!$B$11)*C8+Inputs!$B$16*Inputs!$B$11*D8+Inputs!$B$17*E8)/1000000 | I8: =IF(F8>0,H8*(1-F8),"-") | J8: =H8/Inputs!$B$15*1000 | K8: =H8*Inputs!$B$12
A9: Anthropic | B9: Claude Sonnet 5 | C9: 2 | D9: 0.2 | E9: 10 | F9: 0.5 | G9: S2 | H9: =(Inputs!$B$16*(1-Inputs!$B$11)*C9+Inputs!$B$16*Inputs!$B$11*D9+Inputs!$B$17*E9)/1000000 | I9: =IF(F9>0,H9*(1-F9),"-") | J9: =H9/Inputs!$B$15*1000 | K9: =H9*Inputs!$B$12
A10: Anthropic | B10: Claude Opus 5 | C10: 5 | D10: 0.5 | E10: 25 | F10: 0.5 | G10: S2 | H10: =(Inputs!$B$16*(1-Inputs!$B$11)*C10+Inputs!$B$16*Inputs!$B$11*D10+Inputs!$B$17*E10)/1000000 | I10: =IF(F10>0,H10*(1-F10),"-") | J10: =H10/Inputs!$B$15*1000 | K10: =H10*Inputs!$B$12
A11: Google | B11: Gemini 3.8 Flash (promo to 2026-12-31) | C11: 0.75 | D11: 0.75 | E11: 3.75 | F11: 0 | G11: S3 | H11: =(Inputs!$B$16*(1-Inputs!$B$11)*C11+Inputs!$B$16*Inputs!$B$11*D11+Inputs!$B$17*E11)/1000000 | I11: =IF(F11>0,H11*(1-F11),"-") | J11: =H11/Inputs!$B$15*1000 | K11: =H11*Inputs!$B$12
A12: Google | B12: Gemini 3.1 Pro (<=200k context) | C12: 2 | D12: 2 | E12: 12 | F12: 0 | G12: S3 | H12: =(Inputs!$B$16*(1-Inputs!$B$11)*C12+Inputs!$B$16*Inputs!$B$11*D12+Inputs!$B$17*E12)/1000000 | I12: =IF(F12>0,H12*(1-F12),"-") | J12: =H12/Inputs!$B$15*1000 | K12: =H12*Inputs!$B$12
A13: Azure OpenAI | B13: gpt-5.4-mini, Global Standard | C13: 0.75 | D13: 0.075 | E13: 4.5 | F13: 0.5 | G13: S4 | H13: =(Inputs!$B$16*(1-Inputs!$B$11)*C13+Inputs!$B$16*Inputs!$B$11*D13+Inputs!$B$17*E13)/1000000 | I13: =IF(F13>0,H13*(1-F13),"-") | J13: =H13/Inputs!$B$15*1000 | K13: =H13*Inputs!$B$12
A14: Azure OpenAI | B14: gpt-5.4-mini, Data Zone (list x1.10 - VERIFY) | C14: 0.825 | D14: 0.0825 | E14: 4.95 | F14: 0 | G14: S4 | H14: =(Inputs!$B$16*(1-Inputs!$B$11)*C14+Inputs!$B$16*Inputs!$B$11*D14+Inputs!$B$17*E14)/1000000 | I14: =IF(F14>0,H14*(1-F14),"-") | J14: =H14/Inputs!$B$15*1000 | K14: =H14*Inputs!$B$12
A16: Row numbers used by Summary!B12 (compare row): 1 = first model row, in table order.
A17: A cached-input price equal to the input price means the vendor publishes no cache discount (Gemini).
A18: Prices EXCLUDE: fine-tuning a vendor model, image input, tool-call overhead tokens, egress, support plans.

Sheet Self-hosted
A1: SELF-HOSTED COST. An open-weights model on a VM you control (Ollama / vLLM). Yellow = inputs.
A3: VM SKU (text, for the record) | B3: Azure NV12ads A10 v5, Linux, UAE North (1x A10 24 GB) | C3: Sources S5-S8 list the SKUs checked. Gulf regions have A10s; T4 and A100 mean leaving the region.
A4: VM price, $ per hour, pay-as-you-go | B4: 1.3 | C4: Linux. Reserved 1-year is roughly 30-40% less; check the calculator.
A5: Hours per month the VM runs | B5: 730 | C5: 730 = always on. A VM that stops at night still pays for its disk.
A6: Minimum VMs for availability | B6: 1 | C6: 1 = one VM, and the service is down when it patches. 2 = a pair.
A7: Sustained requests per hour ONE VM serves | B7: 3000 | C7: MEASURE this with notebook 03 for your model and prompt length (Sources S11).
A8: Utilisation ceiling | B8: 0.6 | C8: Plan at 60%. Queues explode above that - Day 2 S8 shows why.
A9: Ops hours per month | B9: 8 | C9: Patching, model updates, monitoring, on-call. YOUR number (Sources S12).
A10: Loaded cost per engineer hour, $ | B10: 60 | C10: YOUR number.
A11: One-off cost, $ (fine-tune, setup) | B11: 25 | C11: The Day 2 fine-tune took 7 minutes on a free T4; 2 h of A10 is $2.60.
A12: Storage, logs, backups, $ per month | B12: 5
A14: Derived
A15: VMs needed for the peak hour | B15: =ROUNDUP(Inputs!B18/(B7*B8),0) | C15: Formula: peak requests/hour / (capacity x utilisation), rounded up
A16: VMs actually run | B16: =MAX(B15,B6) | C16: Formula: the larger of 'needed for peak' and 'minimum for availability'
A17: Compute, $ per month | B17: =B16*B4*B5 | C17: Formula: VMs x $/hour x hours
A18: Ops labour, $ per month | B18: =B9*B10
A19: Self-hosted total, $ per month | B19: =B17+B18+B12 | C19: Formula: compute + ops + storage. Note it does NOT change with volume until you add a VM.
A20: $ per 1000 requests | B20: =B19/Inputs!B15*1000
A21: $ total over the months, incl. one-off | B21: =B19*Inputs!B12+B11
A22: Share of the time the VMs sit idle | B22: =1-Inputs!B15/(B16*B7*B5) | C22: Formula: 1 - requests/month / (VMs x capacity x hours). High = you are paying for a car park.

Sheet Summary
A1: SUMMARY - what to put in the architecture spec (section 7)
A3: Requests per month | B3: =Inputs!B15
A4: Cheapest API option, $ per month | B4: =MIN('API options'!H4:H14)
A5: Cheapest API option, which | B5: =INDEX('API options'!B4:B14,MATCH(B4,'API options'!H4:H14,0))
A6: Self-hosted, $ per month | B6: ='Self-hosted'!B19
A7: Self-hosted, $ total incl. one-off | B7: ='Self-hosted'!B21
A8: Self-hosted VMs run / idle share | B8: ='Self-hosted'!B16 | C8: ='Self-hosted'!B22
A10: Break-even
A11: Compare self-hosted against API row number | B11: 6 | C11: 1 = first row of the API table. Pick the model that actually passes your quality bar, not the cheapest.
A12: That model | B12: =INDEX('API options'!B4:B14,B11)
A13: Its $ per month at your volume | B13: =INDEX('API options'!H4:H14,B11)
A14: Requests per month where self-hosting costs the same | B14: ='Self-hosted'!B19/(INDEX('API options'!J4:J14,B11)/1000) | C14: Formula: self-hosted $/month / API $/request. Below this volume the API is cheaper on money alone.
A15: Your volume as a share of break-even | B15: =B3/B14
A17: Cost is one row of the decision matrix, not the decision. Data residency, latency and who owns it at 02:00 are the others.

Sheet Sources
A1: SOURCES - every price above, where it was read and when. All verified 2026-09-22. Prices change monthly; re-verify before the room.
A2: Id | B2: Item | C2: Source | D2: Verified | E2: How | F2: Detail / caveat
A3: S1 | B3: OpenAI API list prices, per 1M tokens; cached input; Batch API -50% | C3: https://developers.openai.com/api/docs/pricing | D3: 2026-09-22 | E3: primary (vendor page) | F3: gpt-5.4-mini $0.75 / $0.075 cached / $4.50; gpt-5.4 $2.50 / $0.25 / $15; gpt-5.6-luna $0.20 / $0.02 / $1.20; gpt-5.6-terra $2 / $0.20 / $12. Fine-tuning gpt-4.1-mini: $5 per 1M training tokens, then $0.80 in / $3.20 out.
A4: S2 | B4: Anthropic Claude API prices, per 1M tokens; cache hit = 0.1x input; Batch -50% | C4: https://platform.claude.com/docs/en/about-claude/pricing | D4: 2026-09-22 | E4: primary (vendor page) | F4: Haiku 4.5 $1 / $5; Sonnet 5 $2 / $10 (introductory price made permanent); Opus 5 $5 / $25. Claude in Microsoft Foundry bills the SAME per-token rates through the Azure Marketplace (Claude Consumption Units); US-only inference is x1.1.
A5: S3 | B5: Google Gemini API paid tier, per 1M tokens | C5: https://ai.google.dev/gemini-api/docs/pricing | D5: 2026-09-22 | E5: primary (vendor page) | F5: Gemini 3.8 Flash $0.75 / $3.75 is promotional until 2026-12-31, then $1.50 / $7.50. Gemini 3.1 Pro $2 / $12 up to 200k context. Free tier exists but Google may train on it - not for company data.
A6: S4 | B6: Azure OpenAI Service, pay-as-you-go | C6: https://azure.microsoft.com/en-us/pricing/details/azure-openai/ | D6: 2026-09-22 | E6: SECONDARY for the numbers - the Microsoft page renders prices only in the interactive calculator. Global Standard matches OpenAI list per cloudzero.com/blog/azure-openai-pricing (updated 2026-09-04), which also reports Data Zone at about +10%. Regional (UAE North) is higher again and was not obtainable in writing. | F6: RITESH: open the Azure calculator for UAE North / EU Data Zone before the room and overwrite row 11 of the API table.
A7: S5 | B7: Azure VM NV12ads A10 v5 (1x A10 24 GB, 12 vCPU), Linux, pay-as-you-go, UAE North | C7: https://prices.azure.com/api/retail/prices?$filter=armSkuName eq 'Standard_NV12ads_A10_v5' | D7: 2026-09-22 | E7: primary (Azure retail prices API) | F7: $1.30/h UAE North; $0.91/h East US. NV36ads A10 v5 (whole A10): $4.576/h UAE North, $3.20/h East US. Spot and 1-/3-year reservations are cheaper but not for a first deployment.
A8: S6 | B8: Azure VM NC4as T4 v3 (1x T4 16 GB, 4 vCPU), Linux, pay-as-you-go | C8: https://prices.azure.com/api/retail/prices?$filter=armSkuName eq 'Standard_NC4as_T4_v3' | D8: 2026-09-22 | E8: primary (Azure retail prices API) | F8: $0.526/h East US, $0.658/h West Europe. NOT offered in UAE North / UAE Central / Qatar Central (the API returns no rows) - a T4 means the data leaves the region.
A9: S7 | B9: Azure VM NC24ads A100 v4 (1x A100 80 GB), Linux, pay-as-you-go | C9: https://prices.azure.com/api/retail/prices?$filter=armSkuName eq 'Standard_NC24ads_A100_v4' | D9: 2026-09-22 | E9: primary (Azure retail prices API) | F9: $3.673/h East US, $4.775/h West Europe. Not offered in the Gulf regions. Only needed for models of 30B+ parameters or heavy concurrency.
A10: S8 | B10: Azure VM D4s v5 (4 vCPU, 16 GB, no GPU), Linux, UAE North - the app / API layer | C10: https://prices.azure.com/api/retail/prices?$filter=armSkuName eq 'Standard_D4s_v5' | D10: 2026-09-22 | E10: primary (Azure retail prices API) | F10: $0.235/h UAE North. A small model (1B-3B) also RUNS on this, slowly: the build machine's CPU takes 3-4 s a ticket; two Colab CPU cores exceeded 120 s. Not a serving option.
A11: S9 | B11: AWS EC2 GPU instances, on-demand, us-east-1 | C11: https://www.thundercompute.com/blog/ec2-gpu-instances | D11: 2026-09-22 | E11: secondary (Sept 2026 roundup) | F11: g6.xlarge (1x L4 24 GB) $0.8048/h; g5.xlarge (1x A10G 24 GB) $1.006/h. AWS has a Bahrain and a UAE region; their prices were not checked.
A12: S10 | B12: Tokens per ticket - MEASURED on this repo | C12: data/eval/heldout_20.jsonl + corpus/tickets/tickets_raw.jsonl, Llama 3.2 tokenizer | D12: 2026-09-22 | E12: measured | F12: System prompt 250 tokens. Ticket text: mean 72, median 58, p95 211, max 453 over all 600. JSON reply: mean 57, max 64. Scenario A uses 330 in / 60 out.
A13: S11 | B13: Throughput of one GPU VM - MEASURED on a Colab T4, extrapolated | C13: docs/timing_log.md (notebook 06 T4 run, 2026-09-21) | D13: 2026-09-22 | E13: measured + assumption | F13: Ollama 0.12.10, llama3.2:1b, 100% in GPU memory: median 0.8 s per ticket, one request at a time = ~4,500 tickets/hour sequential. Scenario A plans 3,000/h on an A10 to allow for a 3B model and no batching. Measure YOUR number with notebook 03 before you defend it.
A14: S12 | B14: Ops labour and one-off costs | C14: assumption - no source | D14: 2026-09-22 | E14: assumption | F14: The ops hours and hourly rate are placeholders. They are the largest self-hosted line at low volume; replace them with your own before showing anyone a total.
B16: Not modelled: network egress, private endpoints, support plans, currency (all USD), VAT, volume discounts, reserved instances, a vendor's price change mid-year, the cost of a wrong answer.
